{
  "name": "spaceex_plus_bobs",
  "version": "0.1.0",
  "factorio_version": "0.14",
  "title": "Endgame: Space Ex + Bob's",
  "author": "John K",
  "contact": "jkeywo@yahoo.co.uk",
  "description": "Changes Space Ex to use top tier Bob's mod resources. Based on 'CMHMod Bob's End Game'",
  "dependencies": ["base >= 0.14.0", "SpaceMod >= 0.1.13", "boblibrary >= 0.14.0", "? bobplates >= 0.14.0", "? bobelectronics >= 0.14.0", "? bobpower >= 0.14.0", "? bobmodules >= 0.14.0", "? bobtech >= 0.14.0", "? bobwarfare >= 0.14.0", "? bobconfig >= 0.14.0"]
}